MANIFEST.in
setup.py
opps/__init__.py
opps/infographics/__init__.py
opps/infographics/admin.py
opps/infographics/models.py
opps/infographics/search_indexes.py
opps/infographics/tests.py
opps/infographics/urls.py
opps/infographics/views.py
opps/infographics/migrations/0001_initial.py
opps/infographics/migrations/0002_auto__add_field_infographicbox_channel_name__add_field_infographicbox_.py
opps/infographics/migrations/0003_auto__del_unique_infographic_slug__add_field_infographicboxinfographic.py
opps/infographics/migrations/0004_auto__add_unique_infographic_site_slug.py
opps/infographics/migrations/0005_auto__add_field_infographic_css_text.py
opps/infographics/migrations/0006_auto__add_field_infographicitem_css_text.py
opps/infographics/migrations/__init__.py
opps/infographics/templates/infographics/infographic_detail_css.html
opps/infographics/templates/infographics/infographic_detail_gallery.html
opps/infographics/templates/infographics/infographic_detail_timeline.html
opps/infographics/templates/infographics/infographic_list.html
opps/infographics/templatetags/__init__.py
opps/infographics/templatetags/infographics_tags.py
opps_infographics.egg-info/PKG-INFO
opps_infographics.egg-info/SOURCES.txt
opps_infographics.egg-info/dependency_links.txt
opps_infographics.egg-info/namespace_packages.txt
opps_infographics.egg-info/requires.txt
opps_infographics.egg-info/top_level.txt